MANIFEST.in
README.md
setup.cfg
setup.py
proteusisc/__init__.py
proteusisc/bittypes.py
proteusisc/cabledriver.py
proteusisc/command_queue.py
proteusisc/contracts.py
proteusisc/controllerManager.py
proteusisc/errors.py
proteusisc/frame.py
proteusisc/jtagDevice.py
proteusisc/jtagDeviceDescription.py
proteusisc/jtagDeviceDescriptionNetResolver.py
proteusisc/jtagScanChain.py
proteusisc/jtagStateMachine.py
proteusisc/jtagUtils.py
proteusisc/primitive.py
proteusisc/primitive_defaults.py
proteusisc/promise.py
proteusisc/utils.py
proteusisc.egg-info/PKG-INFO
proteusisc.egg-info/SOURCES.txt
proteusisc.egg-info/dependency_links.txt
proteusisc.egg-info/requires.txt
proteusisc.egg-info/top_level.txt
proteusisc/drivers/__init__.py
proteusisc/drivers/digilentdriver.py
proteusisc/drivers/xilinxPC1driver/__init__.py
proteusisc/drivers/xilinxPC1driver/_xpcu1utils.c
proteusisc/test_utils/__init__.py
proteusisc/test_utils/controller.py
proteusisc/test_utils/device.py
test/test_bit_requirement.py
test/test_custom_bitarray_types.py
test/test_digilent_jtag_controller_driver.py
test/test_functional.py
test/test_jtag_functional_with_XPCU1.py
test/test_jtag_functional_with_digilent.py
test/test_jtag_state_machine.py
test/test_mock_digilent_JTAG_controller.py
test/test_mock_physical_jtag_device.py
test/test_mock_xpcu_JTAG_controller.py
test/test_promise.py
test/test_shift_register.py
test/test_utils.py
test/test_xpcu_jtag_controller_driver.py