Metadata-Version: 1.1
Name: proteusisc
Version: 0.2.0
Summary: Driver framework for In System Configureation (ISC) Controllers (for example, JTAG)
Home-page: https://github.com/diamondman/proteusisc
Author: Jessy Diamond Exum
Author-email: jessy.diamondman@gmail.com
License: LGPL 2.1
Platform: any
Classifier: Development Status :: 2 - Pre-Alpha
Classifier: Intended Audience :: Developers
Classifier: License :: OSI Approved :: GNU Lesser General Public License v2 (LGPLv2)
Classifier: Programming Language :: Python :: 3 :: Only
Classifier: Programming Language :: Python :: 3.5
Classifier: Natural Language :: English
Classifier: Operating System :: POSIX :: Linux
Classifier: Topic :: Scientific/Engineering :: Electronic Design Automation (EDA)
Classifier: Topic :: Software Development :: Embedded Systems
Classifier: Topic :: System :: Hardware
